tests/test_statblock.py
tests/dice/conftest.py
tests/dice/test_dice.py
tests/dice/test_indexing.py
tests/dice/test_instantiation.py
tests/manydice/test_dicepools.py
tests/manydice/test_lazyroll.py
ttrpg_dice/__init__.py
ttrpg_dice/dice.py
ttrpg_dice/manydice.py
ttrpg_dice/statblock.py
ttrpg_dice-0.7.0.dist-info/licenses/LICENSE
ttrpg_dice-0.7.0.dist-info/METADATA
ttrpg_dice-0.7.0.dist-info/WHEEL
ttrpg_dice-0.7.0.dist-info/top_level.txt
ttrpg_dice-0.7.0.dist-info/RECORD
